securityfile/__init__.py
securityfile/main.py
securityfile-1.0.2.dist-info/METADATA
securityfile-1.0.2.dist-info/WHEEL
securityfile-1.0.2.dist-info/entry_points.txt
securityfile-1.0.2.dist-info/top_level.txt
securityfile-1.0.2.dist-info/RECORD
