Metadata-Version: 2.4
Name: securityfile
Version: 1.0.2
Summary: python security
Home-page: 
Author: ASMan
Author-email: 
Keywords: securityfile
Requires-Dist: pycryptodome
Dynamic: author
Dynamic: description
Dynamic: description-content-type
Dynamic: keywords
Dynamic: requires-dist
Dynamic: summary
